DPL_SB2/__init__.py
DPL_SB2-0.0.1.dist-info/LICENSE.txt
DPL_SB2-0.0.1.dist-info/METADATA
DPL_SB2-0.0.1.dist-info/WHEEL
DPL_SB2-0.0.1.dist-info/top_level.txt
DPL_SB2-0.0.1.dist-info/RECORD
