Metadata-Version: 2.1
Name: DPL-SB2
Version: 0.0.1
Summary: adding number
Home-page: https://github.com/qasim1020/DPL_SB2
Author: Saylani Students
Author-email: Someone@domain.com
License: UNKNOWN
Platform: UNKNOWN
Classifier: Programming Language :: Python :: 3
Classifier: License :: OSI Approved :: MIT License
Classifier: Operating System :: OS Independent
